high_taste/__init__.py
high_taste/cli.py
high_taste/server.py
high_taste/server_test.py
high_taste/data/rules/001-assertions-over-exceptions.md
high_taste/data/rules/002-load-resources-once.md
high_taste/data/rules/003-eliminate-deep-nesting.md
high_taste/data/rules/004-dynamic-data-discovery.md
high_taste/data/rules/005-structured-return-types.md
high_taste/data/rules/006-database-transaction-safety.md
high_taste/parsers/__init__.py
high_taste/parsers/ast_matcher.py
high_taste/parsers/ast_matcher_test.py
high_taste/rules/__init__.py
high_taste/rules/parser.py
high_taste/rules/parser_test.py
high_taste/utils/__init__.py
high_taste-0.1.0.dist-info/licenses/LICENSE
high_taste-0.1.0.dist-info/METADATA
high_taste-0.1.0.dist-info/WHEEL
high_taste-0.1.0.dist-info/entry_points.txt
high_taste-0.1.0.dist-info/top_level.txt
high_taste-0.1.0.dist-info/RECORD
