Metadata-Version: 2.4
Name: high-taste
Version: 0.1.0
Summary: MCP server that enforces coding style decisions based on taste and convention
Author-email: Alex Dong <alex@example.com>
License: # Functional Source License, Version 1.1, Apache 2.0 Future License
Project-URL: Homepage, https://github.com/alexdong/high-taste
Project-URL: Repository, https://github.com/alexdong/high-taste
Project-URL: Issues, https://github.com/alexdong/high-taste/issues
Keywords: mcp,linter,code-style,taste,python
Classifier: Development Status :: 4 - Beta
Classifier: Intended Audience :: Developers
Classifier: Programming Language :: Python :: 3
Classifier: Programming Language :: Python :: 3.13
Classifier: Topic :: Software Development :: Quality Assurance
Classifier: Topic :: Software Development :: Libraries :: Python Modules
Requires-Python: >=3.13
License-File: LICENSE
Requires-Dist: pydantic>=2.0.0
Requires-Dist: click>=8.0.0
Requires-Dist: rich>=13.0.0
Requires-Dist: mcp>=1.0.0
Requires-Dist: loguru>=0.7.0
Requires-Dist: importlib_resources>=5.0.0; python_version < "3.9"
Dynamic: license-file
